odoo8_addon_mail_edit-8.0.1.0.0.99.dev5-py2.7-nspkg.pth
odoo8_addon_mail_edit-8.0.1.0.0.99.dev5.dist-info/METADATA
odoo8_addon_mail_edit-8.0.1.0.0.99.dev5.dist-info/RECORD
odoo8_addon_mail_edit-8.0.1.0.0.99.dev5.dist-info/WHEEL
odoo8_addon_mail_edit-8.0.1.0.0.99.dev5.dist-info/namespace_packages.txt
odoo8_addon_mail_edit-8.0.1.0.0.99.dev5.dist-info/top_level.txt
odoo_addons/mail_edit/README.rst
odoo_addons/mail_edit/__init__.py
odoo_addons/mail_edit/__openerp__.py
odoo_addons/mail_edit/i18n/mail_edit.pot
odoo_addons/mail_edit/i18n/nl.po
odoo_addons/mail_edit/models/__init__.py
odoo_addons/mail_edit/models/compose_message.py
odoo_addons/mail_edit/models/res_request_link.py
odoo_addons/mail_edit/security/mail_edit_security.xml
odoo_addons/mail_edit/static/description/icon.png
odoo_addons/mail_edit/static/src/css/mail_edit.css
odoo_addons/mail_edit/static/src/js/mail_edit.js
odoo_addons/mail_edit/static/src/xml/mail_edit.xml
odoo_addons/mail_edit/views/assets.xml
odoo_addons/mail_edit/views/compose_message.xml
odoo_addons/mail_edit/views/res_request_link.xml
